compass/__init__.py
compass/core/__init__.py
compass/core/metric_frame.py
compass/core/report_frame.py
compass/core/reports.py
compass/core/reshape_ex.py
compass/core/transform_ex.py
compass/gui/__init__.py
compass/io/__init__.py
compass/io/read_yaml.py
compass/io/【modifying】dr_results.py
compass/io/modules/__init__.py
compass/io/modules/database.py
compass/plotting/__init__.py
compass/util/__init__.py
compass/util/testing.py
cremma/__init__.py
cremma/core/__init__.py
cremma/core/metric_frame.py
cremma/core/report_frame.py
cremma/core/reports.py
cremma/core/reshape_ex.py
cremma/core/transform_ex.py
cremma/core/metrics/AverageSuccess.py
cremma/core/metrics/Average_Success.py
cremma/core/metrics/BaselineLevel.py
cremma/core/metrics/Failures.py
cremma/core/metrics/Total_Adjustment.py
cremma/core/metrics/WeekOfDayAvg.py
cremma/core/metrics/__init__.py
cremma/core/metrics/create.py
cremma/core/metrics/metric_test.py
cremma/core/metrics/filters/__init__.py
cremma/core/metrics/filters/filter_to.py
cremma/core/metrics/formulas/__init__.py
cremma/core/metrics/formulas/get_timeslot_mean.py
cremma/core/metrics/formulas/get_weekly_cons.py
cremma/gui/__init__.py
cremma/io/__init__.py
cremma/io/read_yaml.py
cremma/io/【modifying】dr_results.py
cremma/io/modules/__init__.py
cremma/io/modules/database.py
cremma/plotting/__init__.py
cremma/util/__init__.py
cremma/util/testing.py
cremma-0.0.4.data/scripts/deploy.py
monocle/__init__.py
monocle/core/__init__.py
monocle/core/metric_frame.py
monocle/core/report_frame.py
monocle/core/reports.py
monocle/core/reshape_ex.py
monocle/core/transform_ex.py
monocle/core/metrics/Average_Success.py
monocle/core/metrics/BaselineLevel.py
monocle/core/metrics/Failures.py
monocle/core/metrics/Total_Adjustment.py
monocle/core/metrics/WeekOfDayAvg.py
monocle/core/metrics/__init__.py
monocle/core/metrics/create.py
monocle/core/metrics/filters/__init__.py
monocle/core/metrics/filters/filter_to.py
monocle/core/metrics/formulas/__init__.py
cremma-0.0.4.dist-info/LICENSE
cremma-0.0.4.dist-info/METADATA
cremma-0.0.4.dist-info/WHEEL
cremma-0.0.4.dist-info/dependency_links.txt
cremma-0.0.4.dist-info/top_level.txt
cremma-0.0.4.dist-info/RECORD
