Metadata-Version: 2.1
Name: cremma
Version: 0.0.4
Summary: Cremma allows to create custom reports based on user-defined metrics.
Home-page: https://github.com/jeanjean1/cremma
Author: Jean-Felix Gerard
Author-email: jfgerard@outlook.com
License: UNKNOWN
Platform: UNKNOWN
Classifier: Programming Language :: Python :: 3
Classifier: License :: OSI Approved :: MIT License
Classifier: Operating System :: OS Independent
Requires-Python: >=3.6
Requires-Dist: pandas
